electra/__init__.py
electra-0.0.3.dist-info/METADATA
electra-0.0.3.dist-info/WHEEL
electra-0.0.3.dist-info/licenses/LICENSE
electra-0.0.3.dist-info/RECORD
