Metadata-Version: 2.3
Name: electra
Version: 0.0.3
Summary: Electra
Project-URL: repository, https://github.com/trevorhobenshield/electra
Author-email: Trevor Hobenshield <trevorhobenshield@gmail.com>
License: MIT License
License-File: LICENSE
Keywords: async,concurrency,electra,http
Classifier: Environment :: Web Environment
Classifier: Intended Audience :: Developers
Classifier: Natural Language :: English
Classifier: Operating System :: MacOS :: MacOS X
Classifier: Operating System :: Microsoft :: Windows
Classifier: Operating System :: Unix
Classifier: Programming Language :: Python
Classifier: Programming Language :: Python :: 3
Classifier: Programming Language :: Python :: 3.10
Classifier: Programming Language :: Python :: 3.11
Classifier: Programming Language :: Python :: 3.12
Classifier: Topic :: Internet :: WWW/HTTP
Classifier: Topic :: Software Development :: Libraries
Classifier: Topic :: Software Development :: Libraries :: Python Modules
Requires-Python: >=3.10.10
Requires-Dist: aiofiles
Requires-Dist: httpx[http2]
Requires-Dist: orjson
Requires-Dist: ruff
Requires-Dist: tqdm
Requires-Dist: uvloop; platform_system != 'Windows'
